recipe_scrapers_sage/__init__.py
recipe_scrapers_sage/_types.py
recipe_scrapers_sage/models.py
recipe_scrapers_sage/utils.py
recipe_scrapers_sage-0.1.0.dist-info/METADATA
recipe_scrapers_sage-0.1.0.dist-info/WHEEL
recipe_scrapers_sage-0.1.0.dist-info/RECORD
