Metadata-Version: 2.1
Name: recipe-scrapers-sage
Version: 0.1.0
Summary: 
Author: Matt Anderson
Author-email: matt@manderscience.com
Requires-Python: >=3.8
Classifier: Programming Language :: Python :: 3
Classifier: Programming Language :: Python :: 3.8
Classifier: Programming Language :: Python :: 3.9
Classifier: Programming Language :: Python :: 3.10
Classifier: Programming Language :: Python :: 3.11
Requires-Dist: recipe-scrapers (>=14)
